_elektron.pyd
elektron-0.2.dist-info/DESCRIPTION.rst
elektron-0.2.dist-info/METADATA
elektron-0.2.dist-info/RECORD
elektron-0.2.dist-info/WHEEL
elektron-0.2.dist-info/metadata.json
elektron-0.2.dist-info/top_level.txt
