Metadata-Version: 2.0
Name: elektron
Version: 0.2
Summary: Operational tools
Home-page: https://nepenthe.me/elektron
Author: Alexander Templeton
Author-email: blakmatr@gmail.com
License: UNKNOWN
Platform: UNKNOWN
